nonebot_plugin_latex-0.0.3.5.dist-info/METADATA
nonebot_plugin_latex-0.0.3.5.dist-info/WHEEL
nonebot_plugin_latex-0.0.3.5.dist-info/entry_points.txt
nonebot_plugin_latex-0.0.3.5.dist-info/licenses/LICENSE
nonebot_plugin_latex/__init__.py
nonebot_plugin_latex/config.py
nonebot_plugin_latex/converter.py
nonebot_plugin_latex/data.py
nonebot_plugin_latex/main.py
nonebot_plugin_latex-0.0.3.5.dist-info/RECORD
