Metadata-Version: 2.1
Name: nonebot-plugin-latex
Version: 0.0.3.5
Summary: 通过互联网公共服务渲染LaTeX公式
Author-Email: Eilles <EillesWan@outlook.com>
License:                 木兰宽松许可证, 第2版
Project-URL: Homepage, https://github.com/EillesWan/nonebot-plugin-latex
Project-URL: Bug Tracker, https://github.com/EillesWan/nonebot-plugin-latex/issues
Requires-Python: <4.0,>=3.9
Requires-Dist: nonebot2>=2.2.0
Requires-Dist: httpx>=0.27.0
Requires-Dist: nonebot-plugin-alconna>=0.48.0
